<?xml version="1.0" encoding="UTF-8"?>
<?xml-stylesheet type="text/xsl" href="books.xsl"?>
<catalog>
	<cd>
	<CATEGORY>Science</CATEGORY>
	<NAME>Concept of Physics</NAME>
	<AUTHOR >H.C. Verma</AUTHOR >
	<PRICE>650</PRICE>
	<COUNTRY> India </COUNTRY>
	</cd>
	<cd>
	<CATEGORY>Comics</CATEGORY>
	<NAME>Marvel</NAME>
	<AUTHOR >Stan Lee</AUTHOR >
	<PRICE>800</PRICE>
	<COUNTRY> USA </COUNTRY>
	</cd>
	<cd>
	<CATEGORY>History</CATEGORY>
	<NAME>The chronics of Budhha</NAME>
	<AUTHOR >Kabir Verman</AUTHOR >
	<PRICE>450</PRICE>
	<COUNTRY> India </COUNTRY>
	</cd>
	<cd>
	<CATEGORY>Cooking</CATEGORY>
	<NAME>The Cooking madness</NAME>
	<AUTHOR >Sanjeev Kapoor</AUTHOR >
	<PRICE>500</PRICE>
	<COUNTRY> India </COUNTRY>
	</cd>
	<cd>
	<CATEGORY>Horror</CATEGORY>
	<NAME>One Night in Jungle</NAME>
	<AUTHOR >Miramee Quinsky</AUTHOR >
	<PRICE>800</PRICE>
	<COUNTRY> Japan </COUNTRY>
	</cd>
	<cd>
	<CATEGORY>Sports</CATEGORY>
	<NAME>Success at my feet</NAME>
	<AUTHOR >Shane Warne</AUTHOR >
	<PRICE>400</PRICE>
	<COUNTRY> Australia </COUNTRY>
	</cd>
</catalog>